goenv/__init__.py
goenv/compat.py
goenv/constants.py
goenv/platform_dependent.py
goenv/utils.py
pygoenv-1.7.0.dist-info/DESCRIPTION.rst
pygoenv-1.7.0.dist-info/METADATA
pygoenv-1.7.0.dist-info/RECORD
pygoenv-1.7.0.dist-info/WHEEL
pygoenv-1.7.0.dist-info/entry_points.txt
pygoenv-1.7.0.dist-info/metadata.json
pygoenv-1.7.0.dist-info/top_level.txt
tests/__init__.py
