Metadata-Version: 2.0
Name: pygoenv
Version: 1.7.0
Summary: Simple environment manager for the Go programming language
Home-page: https://github.com/pwoolcoc/goenv
Author: Paul Woolcock
Author-email: paul@woolcock.us
License: MIT
Platform: UNKNOWN
Requires-Dist: clint (>=0.5.1)
Requires-Dist: docopt (>=0.2.6)
Requires-Dist: nose (>=1.3.7)
Requires-Dist: requests (>=2.2.0)
